ver2/knn_classifier.v
module knn_classifier #(
    parameter DATA_WIDTH = 8,
    parameter NUM_FEATURES = 2,
    parameter NUM_TRAINING = 50,
    parameter K_VALUE = 3
)(
    input wire clk,
    input wire rst,
    input wire start,
    input wire [DATA_WIDTH*NUM_FEATURES-1:0] test_data,
    input wire [DATA_WIDTH-1:0] k_value,
    output reg predicted_class,
    output reg done
);

    localparam IDLE = 3'd0;
    localparam CALC_DISTANCE = 3'd1;
    localparam FIND_MIN_INIT = 3'd2;
    localparam FIND_MIN = 3'd3;
    localparam MARK_MIN = 3'd4;
    localparam CLASSIFY = 3'd5;
    localparam DONE_STATE = 3'd6;

    reg [2:0] state;
    reg [6:0] i_reg;
    reg [6:0] k_counter;
    reg [6:0] min_idx;
    reg [12:0] min_dist;
    
    reg [DATA_WIDTH-1:0] training_data1 [0:NUM_TRAINING-1];
    reg [DATA_WIDTH-1:0] training_data2 [0:NUM_TRAINING-1];
    reg training_label [0:NUM_TRAINING-1];
    reg [12:0] training_distance [0:NUM_TRAINING-1];
    reg used [0:NUM_TRAINING-1];
    
    reg [DATA_WIDTH-1:0] test_feature1, test_feature2;
    reg [6:0] k_reg;
    
    reg [6:0] freq_class0, freq_class1;
    
    integer idx;
    initial begin
        training_data1[0] = 8'd1;   training_data2[0] = 8'd12;  training_label[0] = 0;
        training_data1[1] = 8'd2;   training_data2[1] = 8'd5;   training_label[1] = 0;
        training_data1[2] = 8'd5;   training_data2[2] = 8'd3;   training_label[2] = 1;
        training_data1[3] = 8'd3;   training_data2[3] = 8'd2;   training_label[3] = 1;
        training_data1[4] = 8'd3;   training_data2[4] = 8'd6;   training_label[4] = 0;
        training_data1[5] = 8'd7;   training_data2[5] = 8'd8;   training_label[5] = 1;
        training_data1[6] = 8'd8;   training_data2[6] = 8'd2;   training_label[6] = 1;
        training_data1[7] = 8'd1;   training_data2[7] = 8'd9;   training_label[7] = 0;
        training_data1[8] = 8'd4;   training_data2[8] = 8'd7;   training_label[8] = 0;
        training_data1[9] = 8'd6;   training_data2[9] = 8'd4;   training_label[9] = 1;
        
        for (idx = 10; idx < NUM_TRAINING; idx = idx + 1) begin
            training_data1[idx] = 8'd5;
            training_data2[idx] = 8'd5;
            training_label[idx] = idx[0];
        end
    end

    always @(posedge clk or posedge rst) begin
        if (rst) begin
            state <= IDLE;
            i_reg <= 0;
            k_counter <= 0;
            k_reg <= K_VALUE;
            predicted_class <= 0;
            done <= 0;
            freq_class0 <= 0;
            freq_class1 <= 0;
            min_idx <= 0;
            min_dist <= 13'h1FFF;
            test_feature1 <= 0;
            test_feature2 <= 0;
            for (idx = 0; idx < NUM_TRAINING; idx = idx + 1)
                used[idx] <= 0;
        end else begin
            case (state)
                IDLE: begin
                    done <= 0;
                    if (start) begin
                        test_feature1 <= test_data[15:8];
                        test_feature2 <= test_data[7:0];
                        k_reg <= (k_value > 0 && k_value <= NUM_TRAINING) ? k_value : K_VALUE;
                        i_reg <= 0;
                        k_counter <= 0;
                        freq_class0 <= 0;
                        freq_class1 <= 0;
                        for (idx = 0; idx < NUM_TRAINING; idx = idx + 1)
                            used[idx] <= 0;
                        state <= CALC_DISTANCE;
                    end
                end
                
                CALC_DISTANCE: begin
                    if (i_reg < NUM_TRAINING) begin
                        training_distance[i_reg] <= 
                            ((test_feature1 > training_data1[i_reg]) ? 
                             (test_feature1 - training_data1[i_reg]) : 
                             (training_data1[i_reg] - test_feature1)) +
                            ((test_feature2 > training_data2[i_reg]) ? 
                             (test_feature2 - training_data2[i_reg]) : 
                             (training_data2[i_reg] - test_feature2));
                        i_reg <= i_reg + 1;
                    end else begin
                        i_reg <= 0;
                        state <= FIND_MIN_INIT;
                    end
                end
                
                FIND_MIN_INIT: begin
                    min_dist <= 13'h1FFF;
                    min_idx <= 0;
                    i_reg <= 0;
                    state <= FIND_MIN;
                end
                
                FIND_MIN: begin
                    if (i_reg < NUM_TRAINING) begin
                        if (!used[i_reg] && training_distance[i_reg] < min_dist) begin
                            min_dist <= training_distance[i_reg];
                            min_idx <= i_reg;
                        end
                        i_reg <= i_reg + 1;
                    end else begin
                        state <= MARK_MIN;
                    end
                end
                
                MARK_MIN: begin
                    used[min_idx] <= 1;
                    if (training_label[min_idx] == 0)
                        freq_class0 <= freq_class0 + 1;
                    else
                        freq_class1 <= freq_class1 + 1;
                    
                    k_counter <= k_counter + 1;
                    
                    if (k_counter + 1 >= k_reg)
                        state <= CLASSIFY;
                    else
                        state <= FIND_MIN_INIT;
                end
                
                CLASSIFY: begin
                    predicted_class <= (freq_class1 > freq_class0) ? 1 : 0;
                    done <= 1;
                    state <= DONE_STATE;
                end
                
                DONE_STATE: begin
                    if (!start) begin
                        done <= 0;
                        state <= IDLE;
                    end
                end
            endcase
        end
    end

endmodule

ver3/knn_classifier_tb.v
// ============================================================================
// Comprehensive Testbench for K-NN Classifier
// Verilog-2001 Compatible
// ============================================================================

`timescale 1ns / 1ps

module knn_classifier_tb;

    // Parameters
    parameter DATA_WIDTH = 8;
    parameter NUM_FEATURES = 2;
    parameter NUM_TRAINING = 50;
    parameter K_VALUE = 3;
    parameter CLK_PERIOD = 10;

    // Testbench signals
    reg clk;
    reg rst;
    reg start;
    reg [DATA_WIDTH*NUM_FEATURES-1:0] test_data;
    reg [DATA_WIDTH-1:0] k_value;
    wire predicted_class;
    wire done;

    // Test tracking
    integer test_num;
    integer pass_count;
    integer fail_count;
    integer timeout_counter;
    integer i;  // Loop variable declared at module level
    
    // Performance monitoring
    integer start_time, end_time, total_cycles;

    // Instantiate the DUT (Device Under Test)
    knn_classifier #(
        .DATA_WIDTH(DATA_WIDTH),
        .NUM_FEATURES(NUM_FEATURES),
        .NUM_TRAINING(NUM_TRAINING),
        .K_VALUE(K_VALUE)
    ) dut (
        .clk(clk),
        .rst(rst),
        .start(start),
        .test_data(test_data),
        .k_value(k_value),
        .predicted_class(predicted_class),
        .done(done)
    );

    // Clock generation
    initial begin
        clk = 0;
        forever #(CLK_PERIOD/2) clk = ~clk;
    end

    // Helper task to run a test
    task run_test;
        input [7:0] feat1;
        input [7:0] feat2;
        input [7:0] k;
        input expected_class;
        input [200*8-1:0] test_description;
        reg actual_class;
        begin
            test_num = test_num + 1;
            $display("\n--- Test %0d: %0s ---", test_num, test_description);
            $display("Input: (%0d, %0d), K=%0d", feat1, feat2, k);
            
            test_data = {feat1, feat2};
            k_value = k;
            start = 1;
            #CLK_PERIOD;
            start = 0;
            
            // Wait for done with timeout
            timeout_counter = 0;
            while (done == 0 && timeout_counter < 1000) begin
                #CLK_PERIOD;
                timeout_counter = timeout_counter + 1;
            end
            
            if (done == 1) begin
                actual_class = predicted_class;
                $display("Result: Class = %0d", predicted_class);
                if (expected_class === 1'bx) begin
                    $display("PASS - Completed (expected result not specified)");
                    pass_count = pass_count + 1;
                end else if (predicted_class === expected_class) begin
                    $display("PASS - Expected: %0d, Got: %0d", expected_class, predicted_class);
                    pass_count = pass_count + 1;
                end else begin
                    $display("FAIL - Expected: %0d, Got: %0d", expected_class, predicted_class);
                    fail_count = fail_count + 1;
                end
                #(CLK_PERIOD*3);
            end else begin
                $display("FAIL - TIMEOUT waiting for done signal!");
                fail_count = fail_count + 1;
            end
        end
    endtask

    // Main test stimulus
    initial begin
        // Initialize
        rst = 1;
        start = 0;
        test_data = 0;
        k_value = K_VALUE;
        test_num = 0;
        pass_count = 0;
        fail_count = 0;
        
        // Create waveform dump
        $dumpfile("knn_classifier.vcd");
        $dumpvars(0, knn_classifier_tb);
        
        // Reset sequence
        #(CLK_PERIOD*2);
        rst = 0;
        #(CLK_PERIOD*2);
        
        $display("\n========================================");
        $display("K-NN Classifier Comprehensive Test Suite");
        $display("K = %0d, Training Samples = %0d", K_VALUE, NUM_TRAINING);
        $display("========================================\n");

        // ====================================================================
        // BASIC FUNCTIONALITY TESTS
        // ====================================================================
        $display("\n========================================");
        $display("SECTION 1: Basic Functionality Tests");
        $display("========================================");

        run_test(8'd4, 8'd8, 8'd3, 1'b0, "Basic Test 1 - Near Class 0 cluster");
        run_test(8'd2, 8'd3, 8'd3, 1'b1, "Basic Test 2 - Near Class 1 cluster");
        run_test(8'd7, 8'd7, 8'd3, 1'b1, "Basic Test 3 - Very close to (7,8) Class 1");
        run_test(8'd1, 8'd1, 8'd5, 1'b1, "Basic Test 4 - K=5 variant");
        run_test(8'd8, 8'd8, 8'd3, 1'b1, "Basic Test 5 - Corner point");

        // ====================================================================
        // K VALUE VARIATION TESTS
        // ====================================================================
        $display("\n========================================");
        $display("SECTION 2: K Value Variation Tests");
        $display("========================================");

        run_test(8'd4, 8'd8, 8'd1, 1'b0, "K=1 (Nearest neighbor only)");
        run_test(8'd4, 8'd8, 8'd3, 1'b0, "K=3 (same point)");
        run_test(8'd4, 8'd8, 8'd5, 1'b0, "K=5 (same point)");
        run_test(8'd4, 8'd8, 8'd7, 1'b0, "K=7 (same point)");
        run_test(8'd4, 8'd8, 8'd10, 1'b0, "K=10 (large K)");
        
        // ====================================================================
        // TIE BREAKER SCENARIOS
        // ====================================================================
        $display("\n========================================");
        $display("SECTION 3: Tie Breaker Scenarios");
        $display("========================================");

        run_test(8'd5, 8'd5, 8'd2, 1'bx, "Tie scenario - equidistant point");
        run_test(8'd4, 8'd5, 8'd4, 1'bx, "K=4 potential tie");
        run_test(8'd5, 8'd6, 8'd6, 1'bx, "K=6 potential tie");

        // ====================================================================
        // EDGE CASES
        // ====================================================================
        $display("\n========================================");
        $display("SECTION 4: Edge Cases");
        $display("========================================");

        run_test(8'd0, 8'd0, 8'd3, 1'bx, "Minimum coordinates (0,0)");
        run_test(8'd255, 8'd255, 8'd3, 1'bx, "Maximum coordinates (255,255)");
        run_test(8'd0, 8'd255, 8'd3, 1'bx, "Extreme diagonal (0,255)");
        run_test(8'd255, 8'd0, 8'd3, 1'bx, "Extreme diagonal (255,0)");

        run_test(8'd1, 8'd12, 8'd3, 1'b0, "Exact match - Training sample 0");
        run_test(8'd7, 8'd8, 8'd3, 1'b1, "Exact match - Training sample 5");
        run_test(8'd4, 8'd7, 8'd3, 1'b0, "Exact match - Training sample 8");

        run_test(8'd5, 8'd5, 8'd1, 1'bx, "K=1 minimum");
        run_test(8'd5, 8'd5, 8'd50, 1'bx, "K=50 maximum (all training samples)");

        // ====================================================================
        // RAPID FIRE TESTS
        // ====================================================================
        $display("\n========================================");
        $display("SECTION 5: Rapid Fire Tests");
        $display("========================================");

        run_test(8'd1, 8'd2, 8'd3, 1'bx, "Rapid 1");
        run_test(8'd3, 8'd4, 8'd3, 1'bx, "Rapid 2");
        run_test(8'd5, 8'd6, 8'd3, 1'bx, "Rapid 3");
        run_test(8'd7, 8'd8, 8'd3, 1'b1, "Rapid 4 - exact match");
        run_test(8'd9, 8'd10, 8'd3, 1'bx, "Rapid 5");

        // ====================================================================
        // RESET DURING OPERATION TEST
        // ====================================================================
        $display("\n========================================");
        $display("SECTION 6: Reset During Operation");
        $display("========================================");

        test_num = test_num + 1;
        $display("\n--- Test %0d: Reset during computation ---", test_num);
        test_data = {8'd5, 8'd5};
        k_value = 8'd3;
        start = 1;
        #CLK_PERIOD;
        start = 0;
        
        #(CLK_PERIOD * 10);
        $display("Applying reset mid-computation...");
        rst = 1;
        #(CLK_PERIOD * 2);
        rst = 0;
        #(CLK_PERIOD * 2);
        
        if (done == 0 && dut.state == 0) begin
            $display("PASS - Reset recovered properly");
            pass_count = pass_count + 1;
        end else begin
            $display("FAIL - Reset did not recover");
            fail_count = fail_count + 1;
        end

        // ====================================================================
        // INVALID K VALUES
        // ====================================================================
        $display("\n========================================");
        $display("SECTION 7: Invalid K Values");
        $display("========================================");

        run_test(8'd5, 8'd5, 8'd0, 1'bx, "K=0 (invalid, should use default)");
        run_test(8'd5, 8'd5, 8'd100, 1'bx, "K=100 (exceeds NUM_TRAINING)");

        // ====================================================================
        // STRESS TEST
        // ====================================================================
        $display("\n========================================");
        $display("SECTION 8: Stress Test");
        $display("========================================");

        $display("\nRunning 20 sequential classifications...");
        
        for (i = 1; i <= 20; i = i + 1) begin
            test_data = {i[7:0], i[7:0] + 8'd5};
            k_value = 8'd3;
            start = 1;
            #CLK_PERIOD;
            start = 0;
            
            // Wait for done
            timeout_counter = 0;
            while (done == 0 && timeout_counter < 1000) begin
                #CLK_PERIOD;
                timeout_counter = timeout_counter + 1;
            end
            
            if (done == 1) begin
                $display("Stress test %0d: Input=(%0d,%0d), Result=%0d", 
                         i, i[7:0], i[7:0] + 8'd5, predicted_class);
            end else begin
                $display("Stress test %0d: TIMEOUT", i);
            end
            #(CLK_PERIOD*2);
        end
        
        $display("Stress test completed");
        pass_count = pass_count + 20;
        test_num = test_num + 20;

        // ====================================================================
        // FINAL SUMMARY
        // ====================================================================
        #(CLK_PERIOD*10);
        
        $display("\n========================================");
        $display("TEST SUMMARY");
        $display("========================================");
        $display("Total Tests Run: %0d", test_num);
        $display("Passed: %0d", pass_count);
        $display("Failed: %0d", fail_count);
        if (test_num > 0)
            $display("Pass Rate: %0d%%", (pass_count * 100) / test_num);
        $display("========================================");
        
        if (fail_count == 0) begin
            $display("\n*** ALL TESTS PASSED! ***\n");
        end else begin
            $display("\n*** SOME TESTS FAILED ***\n");
        end
        
        $finish;
    end

    // Extended timeout watchdog
    initial begin
        #(CLK_PERIOD * 500000);
        $display("\n\nERROR: Global simulation timeout!");
        $display("Test was running: %0d", test_num);
        $finish;
    end

    // Performance monitoring
    always @(posedge start) begin
        start_time = $time;
    end
    
    always @(posedge done) begin
        end_time = $time;
        total_cycles = (end_time - start_time) / CLK_PERIOD;
        $display("Performance: %0d clock cycles (%0d ns)", total_cycles, end_time - start_time);
    end

endmodule

ver3/knn_classifier.vcd
$date
	Mon Feb  9 14:03:13 2026
$end
$version
	Icarus Verilog
$end
$timescale
	1ps
$end
$scope module knn_classifier_tb $end
$var wire 1 ! predicted_class $end
$var wire 1 " done $end
$var parameter 32 # CLK_PERIOD $end
$var parameter 32 $ DATA_WIDTH $end
$var parameter 32 % K_VALUE $end
$var parameter 32 & NUM_FEATURES $end
$var parameter 32 ' NUM_TRAINING $end
$var reg 1 ( clk $end
$var reg 8 ) k_value [7:0] $end
$var reg 1 * rst $end
$var reg 1 + start $end
$var reg 16 , test_data [15:0] $end
$var integer 32 - end_time [31:0] $end
$var integer 32 . fail_count [31:0] $end
$var integer 32 / i [31:0] $end
$var integer 32 0 pass_count [31:0] $end
$var integer 32 1 start_time [31:0] $end
$var integer 32 2 test_num [31:0] $end
$var integer 32 3 timeout_counter [31:0] $end
$var integer 32 4 total_cycles [31:0] $end
$scope module dut $end
$var wire 1 ( clk $end
$var wire 8 5 k_value [7:0] $end
$var wire 1 * rst $end
$var wire 1 + start $end
$var wire 16 6 test_data [15:0] $end
$var parameter 3 7 CALC_DISTANCE $end
$var parameter 3 8 CLASSIFY $end
$var parameter 32 9 DATA_WIDTH $end
$var parameter 3 : DONE_STATE $end
$var parameter 3 ; FIND_MIN $end
$var parameter 3 < FIND_MIN_INIT $end
$var parameter 3 = IDLE $end
$var parameter 32 > K_VALUE $end
$var parameter 3 ? MARK_MIN $end
$var parameter 32 @ NUM_FEATURES $end
$var parameter 32 A NUM_TRAINING $end
$var reg 1 " done $end
$var reg 7 B freq_class0 [6:0] $end
$var reg 7 C freq_class1 [6:0] $end
$var reg 7 D i_reg [6:0] $end
$var reg 7 E k_counter [6:0] $end
$var reg 7 F k_reg [6:0] $end
$var reg 13 G min_dist [12:0] $end
$var reg 7 H min_idx [6:0] $end
$var reg 1 ! predicted_class $end
$var reg 3 I state [2:0] $end
$var reg 8 J test_feature1 [7:0] $end
$var reg 8 K test_feature2 [7:0] $end
$var integer 32 L idx [31:0] $end
$upscope $end
$scope task run_test $end
$var reg 1 M actual_class $end
$var reg 1 N expected_class $end
$var reg 8 O feat1 [7:0] $end
$var reg 8 P feat2 [7:0] $end
$var reg 8 Q k [7:0] $end
$var reg 1600 R test_description [1599:0] $end
$upscope $end
$upscope $end
$enddefinitions $end
$comment Show the parameter values. $end
$dumpall
b110010 A
b10 @
b100 ?
b11 >
b0 =
b10 <
b11 ;
b110 :
b1000 9
b101 8
b1 7
b110010 '
b10 &
b11 %
b1000 $
b1010 #
$end
#0
$dumpvars
bx R
bx Q
bx P
bx O
xN
xM
b110010 L
b0 K
b0 J
b0 I
b0 H
b1111111111111 G
b11 F
b0 E
b0 D
b0 C
b0 B
b0 6
b11 5
bx 4
bx 3
b0 2
bx 1
b0 0
bx /
b0 .
bx -
b0 ,
0+
1*
b11 )
0(
0"
0!
$end
#5000
b110010 L
1(
#10000
0(
#15000
b110010 L
1(
#20000
0(
0*
#25000
1(
#30000
0(
#35000
1(
#40000
b101000 1
0(
1+
b10000001000 ,
b10000001000 6
b1 2
b100001001100001011100110110100101100011001000000101010001100101011100110111010000100000001100010010000000101101001000000100111001100101011000010111001000100000010000110110110001100001011100110111001100100000001100000010000001100011011011000111010101110011011101000110010101110010 R
0N
b11 Q
b1000 P
b100 O
#45000
b1 I
b1000 K
b100 J
b110010 L
1(
#50000
0(
b0 3
0+
#55000
b1 D
1(
#60000
0(
b1 3
#65000
b10 D
1(
#70000
0(
b10 3
#75000
b11 D
1(
#80000
0(
b11 3
#85000
b100 D
1(
#90000
0(
b100 3
#95000
b101 D
1(
#100000
0(
b101 3
#105000
b110 D
1(
#110000
0(
b110 3
#115000
b111 D
1(
#120000
0(
b111 3
#125000
b1000 D
1(
#130000
0(
b1000 3
#135000
b1001 D
1(
#140000
0(
b1001 3
#145000
b1010 D
1(
#150000
0(
b1010 3
#155000
b1011 D
1(
#160000
0(
b1011 3
#165000
b1100 D
1(
#170000
0(
b1100 3
#175000
b1101 D
1(
#180000
0(
b1101 3
#185000
b1110 D
1(
#190000
0(
b1110 3
#195000
b1111 D
1(
#200000
0(
b1111 3
#205000
b10000 D
1(
#210000
0(
b10000 3
#215000
b10001 D
1(
#220000
0(
b10001 3
#225000
b10010 D
1(
#230000
0(
b10010 3
#235000
b10011 D
1(
#240000
0(
b10011 3
#245000
b10100 D
1(
#250000
0(
b10100 3
#255000
b10101 D
1(
#260000
0(
b10101 3
#265000
b10110 D
1(
#270000
0(
b10110 3
#275000
b10111 D
1(
#280000
0(
b10111 3
#285000
b11000 D
1(
#290000
0(
b11000 3
#295000
b11001 D
1(
#300000
0(
b11001 3
#305000
b11010 D
1(
#310000
0(
b11010 3
#315000
b11011 D
1(
#320000
0(
b11011 3
#325000
b11100 D
1(
#330000
0(
b11100 3
#335000
b11101 D
1(
#340000
0(
b11101 3
#345000
b11110 D
1(
#350000
0(
b11110 3
#355000
b11111 D
1(
#360000
0(
b11111 3
#365000
b100000 D
1(
#370000
0(
b100000 3
#375000
b100001 D
1(
#380000
0(
b100001 3
#385000
b100010 D
1(
#390000
0(
b100010 3
#395000
b100011 D
1(
#400000
0(
b100011 3
#405000
b100100 D
1(
#410000
0(
b100100 3
#415000
b100101 D
1(
#420000
0(
b100101 3
#425000
b100110 D
1(
#430000
0(
b100110 3
#435000
b100111 D
1(
#440000
0(
b100111 3
#445000
b101000 D
1(
#450000
0(
b101000 3
#455000
b101001 D
1(
#460000
0(
b101001 3
#465000
b101010 D
1(
#470000
0(
b101010 3
#475000
b101011 D
1(
#480000
0(
b101011 3
#485000
b101100 D
1(
#490000
0(
b101100 3
#495000
b101101 D
1(
#500000
0(
b101101 3
#505000
b101110 D
1(
#510000
0(
b101110 3
#515000
b101111 D
1(
#520000
0(
b101111 3
#525000
b110000 D
1(
#530000
0(
b110000 3
#535000
b110001 D
1(
#540000
0(
b110001 3
#545000
b110010 D
1(
#550000
0(
b110010 3
#555000
b10 I
b0 D
1(
#560000
0(
b110011 3
#565000
b11 I
1(
#570000
0(
b110100 3
#575000
b1 D
b111 G
1(
#580000
0(
b110101 3
#585000
b10 D
b1 H
b101 G
1(
#590000
0(
b110110 3
#595000
b11 D
1(
#600000
0(
b110111 3
#605000
b100 D
1(
#610000
0(
b111000 3
#615000
b101 D
b100 H
b11 G
1(
#620000
0(
b111001 3
#625000
b110 D
1(
#630000
0(
b111010 3
#635000
b111 D
1(
#640000
0(
b111011 3
#645000
b1000 D
1(
#650000
0(
b111100 3
#655000
b1001 D
b1000 H
b1 G
1(
#660000
0(
b111101 3
#665000
b1010 D
1(
#670000
0(
b111110 3
#675000
b1011 D
1(
#680000
0(
b111111 3
#685000
b1100 D
1(
#690000
0(
b1000000 3
#695000
b1101 D
1(
#700000
0(
b1000001 3
#705000
b1110 D
1(
#710000
0(
b1000010 3
#715000
b1111 D
1(
#720000
0(
b1000011 3
#725000
b10000 D
1(
#730000
0(
b1000100 3
#735000
b10001 D
1(
#740000
0(
b1000101 3
#745000
b10010 D
1(
#750000
0(
b1000110 3
#755000
b10011 D
1(
#760000
0(
b1000111 3
#765000
b10100 D
1(
#770000
0(
b1001000 3
#775000
b10101 D
1(
#780000
0(
b1001001 3
#785000
b10110 D
1(
#790000
0(
b1001010 3
#795000
b10111 D
1(
#800000
0(
b1001011 3
#805000
b11000 D
1(
#810000
0(
b1001100 3
#815000
b11001 D
1(
#820000
0(
b1001101 3
#825000
b11010 D
1(
#830000
0(
b1001110 3
#835000
b11011 D
1(
#840000
0(
b1001111 3
#845000
b11100 D
1(
#850000
0(
b1010000 3
#855000
b11101 D
1(
#860000
0(
b1010001 3
#865000
b11110 D
1(
#870000
0(
b1010010 3
#875000
b11111 D
1(
#880000
0(
b1010011 3
#885000
b100000 D
1(
#890000
0(
b1010100 3
#895000
b100001 D
1(
#900000
0(
b1010101 3
#905000
b100010 D
1(
#910000
0(
b1010110 3
#915000
b100011 D
1(
#920000
0(
b1010111 3
#925000
b100100 D
1(
#930000
0(
b1011000 3
#935000
b100101 D
1(
#940000
0(
b1011001 3
#945000
b100110 D
1(
#950000
0(
b1011010 3
#955000
b100111 D
1(
#960000
0(
b1011011 3
#965000
b101000 D
1(
#970000
0(
b1011100 3
#975000
b101001 D
1(
#980000
0(
b1011101 3
#985000
b101010 D
1(
#990000
0(
b1011110 3
#995000
b101011 D
1(
#1000000
0(
b1011111 3
#1005000
b101100 D
1(
#1010000
0(
b1100000 3
#1015000
b101101 D
1(
#1020000
0(
b1100001 3
#1025000
b101110 D
1(
#1030000
0(
b1100010 3
#1035000
b101111 D
1(
#1040000
0(
b1100011 3
#1045000
b110000 D
1(
#1050000
0(
b1100100 3
#1055000
b110001 D
1(
#1060000
0(
b1100101 3
#1065000
b110010 D
1(
#1070000
0(
b1100110 3
#1075000
b100 I
1(
#1080000
0(
b1100111 3
#1085000
b10 I
b1 E
b1 B
1(
#1090000
0(
b1101000 3
#1095000
b11 I
b0 D
b0 H
b1111111111111 G
1(
#1100000
0(
b1101001 3
#1105000
b1 D
b111 G
1(
#1110000
0(
b1101010 3
#1115000
b10 D
b1 H
b101 G
1(
#1120000
0(
b1101011 3
#1125000
b11 D
1(
#1130000
0(
b1101100 3
#1135000
b100 D
1(
#1140000
0(
b1101101 3
#1145000
b101 D
b100 H
b11 G
1(
#1150000
0(
b1101110 3
#1155000
b110 D
1(
#1160000
0(
b1101111 3
#1165000
b111 D
1(
#1170000
0(
b1110000 3
#1175000
b1000 D
1(
#1180000
0(
b1110001 3
#1185000
b1001 D
1(
#1190000
0(
b1110010 3
#1195000
b1010 D
1(
#1200000
0(
b1110011 3
#1205000
b1011 D
1(
#1210000
0(
b1110100 3
#1215000
b1100 D
1(
#1220000
0(
b1110101 3
#1225000
b1101 D
1(
#1230000
0(
b1110110 3
#1235000
b1110 D
1(
#1240000
0(
b1110111 3
#1245000
b1111 D
1(
#1250000
0(
b1111000 3
#1255000
b10000 D
1(
#1260000
0(
b1111001 3
#1265000
b10001 D
1(
#1270000
0(
b1111010 3
#1275000
b10010 D
1(
#1280000
0(
b1111011 3
#1285000
b10011 D
1(
#1290000
0(
b1111100 3
#1295000
b10100 D
1(
#1300000
0(
b1111101 3
#1305000
b10101 D
1(
#1310000
0(
b1111110 3
#1315000
b10110 D
1(
#1320000
0(
b1111111 3
#1325000
b10111 D
1(
#1330000
0(
b10000000 3
#1335000
b11000 D
1(
#1340000
0(
b10000001 3
#1345000
b11001 D
1(
#1350000
0(
b10000010 3
#1355000
b11010 D
1(
#1360000
0(
b10000011 3
#1365000
b11011 D
1(
#1370000
0(
b10000100 3
#1375000
b11100 D
1(
#1380000
0(
b10000101 3
#1385000
b11101 D
1(
#1390000
0(
b10000110 3
#1395000
b11110 D
1(
#1400000
0(
b10000111 3
#1405000
b11111 D
1(
#1410000
0(
b10001000 3
#1415000
b100000 D
1(
#1420000
0(
b10001001 3
#1425000
b100001 D
1(
#1430000
0(
b10001010 3
#1435000
b100010 D
1(
#1440000
0(
b10001011 3
#1445000
b100011 D
1(
#1450000
0(
b10001100 3
#1455000
b100100 D
1(
#1460000
0(
b10001101 3
#1465000
b100101 D
1(
#1470000
0(
b10001110 3
#1475000
b100110 D
1(
#1480000
0(
b10001111 3
#1485000
b100111 D
1(
#1490000
0(
b10010000 3
#1495000
b101000 D
1(
#1500000
0(
b10010001 3
#1505000
b101001 D
1(
#1510000
0(
b10010010 3
#1515000
b101010 D
1(
#1520000
0(
b10010011 3
#1525000
b101011 D
1(
#1530000
0(
b10010100 3
#1535000
b101100 D
1(
#1540000
0(
b10010101 3
#1545000
b101101 D
1(
#1550000
0(
b10010110 3
#1555000
b101110 D
1(
#1560000
0(
b10010111 3
#1565000
b101111 D
1(
#1570000
0(
b10011000 3
#1575000
b110000 D
1(
#1580000
0(
b10011001 3
#1585000
b110001 D
1(
#1590000
0(
b10011010 3
#1595000
b110010 D
1(
#1600000
0(
b10011011 3
#1605000
b100 I
1(
#1610000
0(
b10011100 3
#1615000
b10 I
b10 E
b10 B
1(
#1620000
0(
b10011101 3
#1625000
b11 I
b0 D
b0 H
b1111111111111 G
1(
#1630000
0(
b10011110 3
#1635000
b1 D
b111 G
1(
#1640000
0(
b10011111 3
#1645000
b10 D
b1 H
b101 G
1(
#1650000
0(
b10100000 3
#1655000
b11 D
1(
#1660000
0(
b10100001 3
#1665000
b100 D
1(
#1670000
0(
b10100010 3
#1675000
b101 D
1(
#1680000
0(
b10100011 3
#1685000
b110 D
b101 H
b11 G
1(
#1690000
0(
b10100100 3
#1695000
b111 D
1(
#1700000
0(
b10100101 3
#1705000
b1000 D
1(
#1710000
0(
b10100110 3
#1715000
b1001 D
1(
#1720000
0(
b10100111 3
#1725000
b1010 D
1(
#1730000
0(
b10101000 3
#1735000
b1011 D
1(
#1740000
0(
b10101001 3
#1745000
b1100 D
1(
#1750000
0(
b10101010 3
#1755000
b1101 D
1(
#1760000
0(
b10101011 3
#1765000
b1110 D
1(
#1770000
0(
b10101100 3
#1775000
b1111 D
1(
#1780000
0(
b10101101 3
#1785000
b10000 D
1(
#1790000
0(
b10101110 3
#1795000
b10001 D
1(
#1800000
0(
b10101111 3
#1805000
b10010 D
1(
#1810000
0(
b10110000 3
#1815000
b10011 D
1(
#1820000
0(
b10110001 3
#1825000
b10100 D
1(
#1830000
0(
b10110010 3
#1835000
b10101 D
1(
#1840000
0(
b10110011 3
#1845000
b10110 D
1(
#1850000
0(
b10110100 3
#1855000
b10111 D
1(
#1860000
0(
b10110101 3
#1865000
b11000 D
1(
#1870000
0(
b10110110 3
#1875000
b11001 D
1(
#1880000
0(
b10110111 3
#1885000
b11010 D
1(
#1890000
0(
b10111000 3
#1895000
b11011 D
1(
#1900000
0(
b10111001 3
#1905000
b11100 D
1(
#1910000
0(
b10111010 3
#1915000
b11101 D
1(
#1920000
0(
b10111011 3
#1925000
b11110 D
1(
#1930000
0(
b10111100 3
#1935000
b11111 D
1(
#1940000
0(
b10111101 3
#1945000
b100000 D
1(
#1950000
0(
b10111110 3
#1955000
b100001 D
1(
#1960000
0(
b10111111 3
#1965000
b100010 D
1(
#1970000
0(
b11000000 3
#1975000
b100011 D
1(
#1980000
0(
b11000001 3
#1985000
b100100 D
1(
#1990000
0(
b11000010 3
#1995000
b100101 D
1(
#2000000
0(
b11000011 3
#2005000
b100110 D
1(
#2010000
0(
b11000100 3
#2015000
b100111 D
1(
#2020000
0(
b11000101 3
#2025000
b101000 D
1(
#2030000
0(
b11000110 3
#2035000
b101001 D
1(
#2040000
0(
b11000111 3
#2045000
b101010 D
1(
#2050000
0(
b11001000 3
#2055000
b101011 D
1(
#2060000
0(
b11001001 3
#2065000
b101100 D
1(
#2070000
0(
b11001010 3
#2075000
b101101 D
1(
#2080000
0(
b11001011 3
#2085000
b101110 D
1(
#2090000
0(
b11001100 3
#2095000
b101111 D
1(
#2100000
0(
b11001101 3
#2105000
b110000 D
1(
#2110000
0(
b11001110 3
#2115000
b110001 D
1(
#2120000
0(
b11001111 3
#2125000
b110010 D
1(
#2130000
0(
b11010000 3
#2135000
b100 I
1(
#2140000
0(
b11010001 3
#2145000
b101 I
b11 E
b1 C
1(
#2150000
0(
b11010010 3
#2155000
b11010011 4
b100001101011 -
b110 I
1"
1(
#2160000
0(
b1 0
0M
b11010011 3
#2165000
b0 I
0"
1(
#2170000
0(
#2175000
1(
#2180000
0(
#2185000
1(
#2190000
b100010001110 1
0(
1+
b1000000011 ,
b1000000011 6
b10 2
b100001001100001011100110110100101100011001000000101010001100101011100110111010000100000001100100010000000101101001000000100111001100101011000010111001000100000010000110110110001100001011100110111001100100000001100010010000001100011011011000111010101110011011101000110010101110010 R
1N
b11 P
b10 O
#2195000
b1 I
b0 C
b0 B
b0 E
b0 D
b11 K
b10 J
b110010 L
1(
#2200000
0(
b0 3
0+
#2205000
b1 D
1(
#2210000
0(
b1 3
#2215000
b10 D
1(
#2220000
0(
b10 3
#2225000
b11 D
1(
#2230000
0(
b11 3
#2235000
b100 D
1(
#2240000
0(
b100 3
#2245000
b101 D
1(
