ver2/knn_classifier.v
module knn_classifier #(
    parameter DATA_WIDTH = 8,
    parameter NUM_FEATURES = 2,
    parameter NUM_TRAINING = 50,
    parameter K_VALUE = 3
)(
    input wire clk,
    input wire rst,
    input wire start,
    input wire [DATA_WIDTH*NUM_FEATURES-1:0] test_data,
    input wire [DATA_WIDTH-1:0] k_value,
    output reg predicted_class,
    output reg done
);

    localparam IDLE = 3'd0;
    localparam CALC_DISTANCE = 3'd1;
    localparam FIND_MIN_INIT = 3'd2;
    localparam FIND_MIN = 3'd3;
    localparam MARK_MIN = 3'd4;
    localparam CLASSIFY = 3'd5;
    localparam DONE_STATE = 3'd6;

    reg [2:0] state;
    reg [6:0] i_reg;
    reg [6:0] k_counter;
    reg [6:0] min_idx;
    reg [12:0] min_dist;
    
    reg [DATA_WIDTH-1:0] training_data1 [0:NUM_TRAINING-1];
    reg [DATA_WIDTH-1:0] training_data2 [0:NUM_TRAINING-1];
    reg training_label [0:NUM_TRAINING-1];
    reg [12:0] training_distance [0:NUM_TRAINING-1];
    reg used [0:NUM_TRAINING-1];
    
    reg [DATA_WIDTH-1:0] test_feature1, test_feature2;
    reg [6:0] k_reg;
    
    reg [6:0] freq_class0, freq_class1;
    
    integer idx;
    initial begin
        training_data1[0] = 8'd1;   training_data2[0] = 8'd12;  training_label[0] = 0;
        training_data1[1] = 8'd2;   training_data2[1] = 8'd5;   training_label[1] = 0;
        training_data1[2] = 8'd5;   training_data2[2] = 8'd3;   training_label[2] = 1;
        training_data1[3] = 8'd3;   training_data2[3] = 8'd2;   training_label[3] = 1;
        training_data1[4] = 8'd3;   training_data2[4] = 8'd6;   training_label[4] = 0;
        training_data1[5] = 8'd7;   training_data2[5] = 8'd8;   training_label[5] = 1;
        training_data1[6] = 8'd8;   training_data2[6] = 8'd2;   training_label[6] = 1;
        training_data1[7] = 8'd1;   training_data2[7] = 8'd9;   training_label[7] = 0;
        training_data1[8] = 8'd4;   training_data2[8] = 8'd7;   training_label[8] = 0;
        training_data1[9] = 8'd6;   training_data2[9] = 8'd4;   training_label[9] = 1;
        
        for (idx = 10; idx < NUM_TRAINING; idx = idx + 1) begin
            training_data1[idx] = 8'd5;
            training_data2[idx] = 8'd5;
            training_label[idx] = idx[0];
        end
    end

    always @(posedge clk or posedge rst) begin
        if (rst) begin
            state <= IDLE;
            i_reg <= 0;
            k_counter <= 0;
            k_reg <= K_VALUE;
            predicted_class <= 0;
            done <= 0;
            freq_class0 <= 0;
            freq_class1 <= 0;
            min_idx <= 0;
            min_dist <= 13'h1FFF;
            test_feature1 <= 0;
            test_feature2 <= 0;
            for (idx = 0; idx < NUM_TRAINING; idx = idx + 1)
                used[idx] <= 0;
        end else begin
            case (state)
                IDLE: begin
                    done <= 0;
                    if (start) begin
                        test_feature1 <= test_data[15:8];
                        test_feature2 <= test_data[7:0];
                        k_reg <= (k_value > 0 && k_value <= NUM_TRAINING) ? k_value : K_VALUE;
                        i_reg <= 0;
                        k_counter <= 0;
                        freq_class0 <= 0;
                        freq_class1 <= 0;
                        for (idx = 0; idx < NUM_TRAINING; idx = idx + 1)
                            used[idx] <= 0;
                        state <= CALC_DISTANCE;
                    end
                end
                
                CALC_DISTANCE: begin
                    if (i_reg < NUM_TRAINING) begin
                        training_distance[i_reg] <= 
                            ((test_feature1 > training_data1[i_reg]) ? 
                             (test_feature1 - training_data1[i_reg]) : 
                             (training_data1[i_reg] - test_feature1)) +
                            ((test_feature2 > training_data2[i_reg]) ? 
                             (test_feature2 - training_data2[i_reg]) : 
                             (training_data2[i_reg] - test_feature2));
                        i_reg <= i_reg + 1;
                    end else begin
                        i_reg <= 0;
                        state <= FIND_MIN_INIT;
                    end
                end
                
                FIND_MIN_INIT: begin
                    min_dist <= 13'h1FFF;
                    min_idx <= 0;
                    i_reg <= 0;
                    state <= FIND_MIN;
                end
                
                FIND_MIN: begin
                    if (i_reg < NUM_TRAINING) begin
                        if (!used[i_reg] && training_distance[i_reg] < min_dist) begin
                            min_dist <= training_distance[i_reg];
                            min_idx <= i_reg;
                        end
                        i_reg <= i_reg + 1;
                    end else begin
                        state <= MARK_MIN;
                    end
                end
                
                MARK_MIN: begin
                    used[min_idx] <= 1;
                    if (training_label[min_idx] == 0)
                        freq_class0 <= freq_class0 + 1;
                    else
                        freq_class1 <= freq_class1 + 1;
                    
                    k_counter <= k_counter + 1;
                    
                    if (k_counter + 1 >= k_reg)
                        state <= CLASSIFY;
                    else
                        state <= FIND_MIN_INIT;
                end
                
                CLASSIFY: begin
                    predicted_class <= (freq_class1 > freq_class0) ? 1 : 0;
                    done <= 1;
                    state <= DONE_STATE;
                end
                
                DONE_STATE: begin
                    if (!start) begin
                        done <= 0;
                        state <= IDLE;
                    end
                end
            endcase
        end
    end

endmodule

ver2/knn_classifier_tb.v
// ============================================================================
// Testbench for K-NN Classifier (Fast Version)
// ============================================================================

`timescale 1ns / 1ps

module knn_classifier_tb;

    // Parameters
    parameter DATA_WIDTH = 8;
    parameter NUM_FEATURES = 2;
    parameter NUM_TRAINING = 50;
    parameter K_VALUE = 3;
    parameter CLK_PERIOD = 10;

    // Testbench signals
    reg clk;
    reg rst;
    reg start;
    reg [DATA_WIDTH*NUM_FEATURES-1:0] test_data;
    reg [DATA_WIDTH-1:0] k_value;
    wire predicted_class;
    wire done;

    // Instantiate the DUT (Device Under Test)
    knn_classifier #(
        .DATA_WIDTH(DATA_WIDTH),
        .NUM_FEATURES(NUM_FEATURES),
        .NUM_TRAINING(NUM_TRAINING),
        .K_VALUE(K_VALUE)
    ) dut (
        .clk(clk),
        .rst(rst),
        .start(start),
        .test_data(test_data),
        .k_value(k_value),
        .predicted_class(predicted_class),
        .done(done)
    );

    // Clock generation
    initial begin
        clk = 0;
        forever #(CLK_PERIOD/2) clk = ~clk;
    end

    // Test stimulus
    integer test_num;
    initial begin
        // Initialize signals
        rst = 1;
        start = 0;
        test_data = 0;
        k_value = K_VALUE;
        test_num = 0;
        
        // Create waveform dump
        $dumpfile("knn_classifier.vcd");
        $dumpvars(0, knn_classifier_tb);
        
        // Wait for reset
        #(CLK_PERIOD*2);
        rst = 0;
        #(CLK_PERIOD*2);
        
        $display("\n========================================");
        $display("K-NN Classifier Testbench");
        $display("K = %0d, Training Samples = %0d", K_VALUE, NUM_TRAINING);
        $display("========================================\n");

        // Test Case 1: Test point (4, 8)
        test_num = 1;
        $display("Test %0d: Input = (4, 8)", test_num);
        test_data = {8'd4, 8'd8};
        k_value = 3;
        start = 1;
        #CLK_PERIOD;
        start = 0;
        
        wait(done == 1);
        $display("Result: Class = %0d\n", predicted_class);
        #(CLK_PERIOD*5);

        // Test Case 2: Test point (2, 3)
        test_num = 2;
        $display("Test %0d: Input = (2, 3)", test_num);
        test_data = {8'd2, 8'd3};
        k_value = 3;
        start = 1;
        #CLK_PERIOD;
        start = 0;
        
        wait(done == 1);
        $display("Result: Class = %0d\n", predicted_class);
        #(CLK_PERIOD*5);

        // Test Case 3: Test point (7, 7)
        test_num = 3;
        $display("Test %0d: Input = (7, 7)", test_num);
        test_data = {8'd7, 8'd7};
        k_value = 3;
        start = 1;
        #CLK_PERIOD;
        start = 0;
        
        wait(done == 1);
        $display("Result: Class = %0d\n", predicted_class);
        #(CLK_PERIOD*5);

        // Test Case 4: Test point (1, 1) with K=5
        test_num = 4;
        $display("Test %0d: Input = (1, 1), K = 5", test_num);
        test_data = {8'd1, 8'd1};
        k_value = 5;
        start = 1;
        #CLK_PERIOD;
        start = 0;
        
        wait(done == 1);
        $display("Result: Class = %0d\n", predicted_class);
        #(CLK_PERIOD*5);

        // Test Case 5: Test point (8, 8)
        test_num = 5;
        $display("Test %0d: Input = (8, 8)", test_num);
        test_data = {8'd8, 8'd8};
        k_value = 3;
        start = 1;
        #CLK_PERIOD;
        start = 0;
        
        wait(done == 1);
        $display("Result: Class = %0d\n", predicted_class);
        #(CLK_PERIOD*10);

        $display("\n========================================");
        $display("All tests completed!");
        $display("========================================\n");
        
        $finish;
    end

    // Timeout watchdog
    initial begin
        #(CLK_PERIOD * 100000);
        $display("\nERROR: Simulation timeout!");
        $finish;
    end

    // Monitor for debugging - updated for fast version
    initial begin
        $monitor("Time=%0t | State=%0d | i=%0d | k_counter=%0d | Done=%b | Class=%b", 
                 $time, dut.state, dut.i_reg, dut.k_counter, done, predicted_class);
    end

endmodule

ver2/knn_classifier.vcd
$date
	Sat Feb  7 22:56:35 2026
$end
$version
	Icarus Verilog
$end
$timescale
	1ps
$end
$scope module knn_classifier_tb $end
$var wire 1 ! predicted_class $end
$var wire 1 " done $end
$var parameter 32 # CLK_PERIOD $end
$var parameter 32 $ DATA_WIDTH $end
$var parameter 32 % K_VALUE $end
$var parameter 32 & NUM_FEATURES $end
$var parameter 32 ' NUM_TRAINING $end
$var reg 1 ( clk $end
$var reg 8 ) k_value [7:0] $end
$var reg 1 * rst $end
$var reg 1 + start $end
$var reg 16 , test_data [15:0] $end
$var integer 32 - test_num [31:0] $end
$scope module dut $end
$var wire 1 ( clk $end
$var wire 8 . k_value [7:0] $end
$var wire 1 * rst $end
$var wire 1 + start $end
$var wire 16 / test_data [15:0] $end
$var parameter 3 0 CALC_DISTANCE $end
$var parameter 3 1 CLASSIFY $end
$var parameter 32 2 DATA_WIDTH $end
$var parameter 3 3 DONE_STATE $end
$var parameter 3 4 FIND_MIN $end
$var parameter 3 5 FIND_MIN_INIT $end
$var parameter 3 6 IDLE $end
$var parameter 32 7 K_VALUE $end
$var parameter 3 8 MARK_MIN $end
$var parameter 32 9 NUM_FEATURES $end
$var parameter 32 : NUM_TRAINING $end
$var reg 1 " done $end
$var reg 7 ; freq_class0 [6:0] $end
$var reg 7 < freq_class1 [6:0] $end
$var reg 7 = i_reg [6:0] $end
$var reg 7 > k_counter [6:0] $end
$var reg 7 ? k_reg [6:0] $end
$var reg 13 @ min_dist [12:0] $end
$var reg 7 A min_idx [6:0] $end
$var reg 1 ! predicted_class $end
$var reg 3 B state [2:0] $end
$var reg 8 C test_feature1 [7:0] $end
$var reg 8 D test_feature2 [7:0] $end
$var integer 32 E idx [31:0] $end
$upscope $end
$upscope $end
$enddefinitions $end
$comment Show the parameter values. $end
$dumpall
b110010 :
b10 9
b100 8
b11 7
b0 6
b10 5
b11 4
b110 3
b1000 2
b101 1
b1 0
b110010 '
b10 &
b11 %
b1000 $
b1010 #
$end
#0
$dumpvars
b110010 E
b0 D
b0 C
b0 B
b0 A
b1111111111111 @
b11 ?
b0 >
b0 =
b0 <
b0 ;
b0 /
b11 .
b0 -
b0 ,
0+
1*
b11 )
0(
0"
0!
$end
#5000
b110010 E
1(
#10000
0(
#15000
b110010 E
1(
#20000
0(
0*
#25000
1(
#30000
0(
#35000
1(
#40000
0(
1+
b10000001000 ,
b10000001000 /
b1 -
#45000
b1 B
b1000 D
b100 C
b110010 E
1(
#50000
0(
0+
#55000
b1 =
1(
#60000
0(
#65000
b10 =
1(
#70000
0(
#75000
b11 =
1(
#80000
0(
#85000
b100 =
1(
#90000
0(
#95000
b101 =
1(
#100000
0(
#105000
b110 =
1(
#110000
0(
#115000
b111 =
1(
#120000
0(
#125000
b1000 =
1(
#130000
0(
#135000
b1001 =
1(
#140000
0(
#145000
b1010 =
1(
#150000
0(
#155000
b1011 =
1(
#160000
0(
#165000
b1100 =
1(
#170000
0(
#175000
b1101 =
1(
#180000
0(
#185000
b1110 =
1(
#190000
0(
#195000
b1111 =
1(
#200000
0(
#205000
b10000 =
1(
#210000
0(
#215000
b10001 =
1(
#220000
0(
#225000
b10010 =
1(
#230000
0(
#235000
b10011 =
1(
#240000
0(
#245000
b10100 =
1(
#250000
0(
#255000
b10101 =
1(
#260000
0(
#265000
b10110 =
1(
#270000
0(
#275000
b10111 =
1(
#280000
0(
#285000
b11000 =
1(
#290000
0(
#295000
b11001 =
1(
#300000
0(
#305000
b11010 =
1(
#310000
0(
#315000
b11011 =
1(
#320000
0(
#325000
b11100 =
1(
#330000
0(
#335000
b11101 =
1(
#340000
0(
#345000
b11110 =
1(
#350000
0(
#355000
b11111 =
1(
#360000
0(
#365000
b100000 =
1(
#370000
0(
#375000
b100001 =
1(
#380000
0(
#385000
b100010 =
1(
#390000
0(
#395000
b100011 =
1(
#400000
0(
#405000
b100100 =
1(
#410000
0(
#415000
b100101 =
1(
#420000
0(
#425000
b100110 =
1(
#430000
0(
#435000
b100111 =
1(
#440000
0(
#445000
b101000 =
1(
#450000
0(
#455000
b101001 =
1(
#460000
0(
#465000
b101010 =
1(
#470000
0(
#475000
b101011 =
1(
#480000
0(
#485000
b101100 =
1(
#490000
0(
#495000
b101101 =
1(
#500000
0(
#505000
b101110 =
1(
#510000
0(
#515000
b101111 =
1(
#520000
0(
#525000
b110000 =
1(
#530000
0(
#535000
b110001 =
1(
#540000
0(
#545000
b110010 =
1(
#550000
0(
#555000
b10 B
b0 =
1(
#560000
0(
#565000
b11 B
1(
#570000
0(
#575000
b1 =
b111 @
1(
#580000
0(
#585000
b10 =
b1 A
b101 @
1(
#590000
0(
#595000
b11 =
1(
#600000
0(
#605000
b100 =
1(
#610000
0(
#615000
b101 =
b100 A
b11 @
1(
#620000
0(
#625000
b110 =
1(
#630000
0(
#635000
b111 =
1(
#640000
0(
#645000
b1000 =
1(
#650000
0(
#655000
b1001 =
b1000 A
b1 @
1(
#660000
0(
#665000
b1010 =
1(
#670000
0(
#675000
b1011 =
1(
#680000
0(
#685000
b1100 =
1(
#690000
0(
#695000
b1101 =
1(
#700000
0(
#705000
b1110 =
1(
#710000
0(
#715000
b1111 =
1(
#720000
0(
#725000
b10000 =
1(
#730000
0(
#735000
b10001 =
1(
#740000
0(
#745000
b10010 =
1(
#750000
0(
#755000
b10011 =
1(
#760000
0(
#765000
b10100 =
1(
#770000
0(
#775000
b10101 =
1(
#780000
0(
#785000
b10110 =
1(
#790000
0(
#795000
b10111 =
1(
#800000
0(
#805000
b11000 =
1(
#810000
0(
#815000
b11001 =
1(
#820000
0(
#825000
b11010 =
1(
#830000
0(
#835000
b11011 =
1(
#840000
0(
#845000
b11100 =
1(
#850000
0(
#855000
b11101 =
1(
#860000
0(
#865000
b11110 =
1(
#870000
0(
#875000
b11111 =
1(
#880000
0(
#885000
b100000 =
1(
#890000
0(
#895000
b100001 =
1(
#900000
0(
#905000
b100010 =
1(
#910000
0(
#915000
b100011 =
1(
#920000
0(
#925000
b100100 =
1(
#930000
0(
#935000
b100101 =
1(
#940000
0(
#945000
b100110 =
1(
#950000
0(
#955000
b100111 =
1(
#960000
0(
#965000
b101000 =
1(
#970000
0(
#975000
b101001 =
1(
#980000
0(
#985000
b101010 =
1(
#990000
0(
#995000
b101011 =
1(
#1000000
0(
#1005000
b101100 =
1(
#1010000
0(
#1015000
b101101 =
1(
#1020000
0(
#1025000
b101110 =
1(
#1030000
0(
#1035000
b101111 =
1(
#1040000
0(
#1045000
b110000 =
1(
#1050000
0(
#1055000
b110001 =
1(
#1060000
0(
#1065000
b110010 =
1(
#1070000
0(
#1075000
b100 B
1(
#1080000
0(
#1085000
b10 B
b1 >
b1 ;
1(
#1090000
0(
#1095000
b11 B
b0 =
b0 A
b1111111111111 @
1(
#1100000
0(
#1105000
b1 =
b111 @
1(
#1110000
0(
#1115000
b10 =
b1 A
b101 @
1(
#1120000
0(
#1125000
b11 =
1(
#1130000
0(
#1135000
b100 =
1(
#1140000
0(
#1145000
b101 =
b100 A
b11 @
1(
#1150000
0(
#1155000
b110 =
1(
#1160000
0(
#1165000
b111 =
1(
#1170000
0(
#1175000
b1000 =
1(
#1180000
0(
#1185000
b1001 =
1(
#1190000
0(
#1195000
b1010 =
1(
#1200000
0(
#1205000
b1011 =
1(
#1210000
0(
#1215000
b1100 =
1(
#1220000
0(
#1225000
b1101 =
1(
#1230000
0(
#1235000
b1110 =
1(
#1240000
0(
#1245000
b1111 =
1(
#1250000
0(
#1255000
b10000 =
1(
#1260000
0(
#1265000
b10001 =
1(
#1270000
0(
#1275000
b10010 =
1(
#1280000
0(
#1285000
b10011 =
1(
#1290000
0(
#1295000
b10100 =
1(
#1300000
0(
#1305000
b10101 =
1(
#1310000
0(
#1315000
b10110 =
1(
#1320000
0(
#1325000
b10111 =
1(
#1330000
0(
#1335000
b11000 =
1(
#1340000
0(
#1345000
b11001 =
1(
#1350000
0(
#1355000
b11010 =
1(
#1360000
0(
#1365000
b11011 =
1(
#1370000
0(
#1375000
b11100 =
1(
#1380000
0(
#1385000
b11101 =
1(
#1390000
0(
#1395000
b11110 =
1(
#1400000
0(
#1405000
b11111 =
1(
#1410000
0(
#1415000
b100000 =
1(
#1420000
0(
#1425000
b100001 =
1(
#1430000
0(
#1435000
b100010 =
1(
#1440000
0(
#1445000
b100011 =
1(
#1450000
0(
#1455000
b100100 =
1(
#1460000
0(
#1465000
b100101 =
1(
#1470000
0(
#1475000
b100110 =
1(
#1480000
0(
#1485000
b100111 =
1(
#1490000
0(
#1495000
b101000 =
1(
#1500000
0(
#1505000
b101001 =
1(
#1510000
0(
#1515000
b101010 =
1(
#1520000
0(
#1525000
b101011 =
1(
#1530000
0(
#1535000
b101100 =
1(
#1540000
0(
#1545000
b101101 =
1(
#1550000
0(
#1555000
b101110 =
1(
#1560000
0(
#1565000
b101111 =
1(
#1570000
0(
#1575000
b110000 =
1(
#1580000
0(
#1585000
b110001 =
1(
#1590000
0(
#1595000
b110010 =
1(
#1600000
0(
#1605000
b100 B
1(
#1610000
0(
#1615000
b10 B
b10 >
b10 ;
1(
#1620000
0(
#1625000
b11 B
b0 =
b0 A
b1111111111111 @
1(
#1630000
0(
#1635000
b1 =
b111 @
1(
#1640000
0(
#1645000
b10 =
b1 A
b101 @
1(
#1650000
0(
#1655000
b11 =
1(
#1660000
0(
#1665000
b100 =
1(
#1670000
0(
#1675000
b101 =
1(
#1680000
0(
#1685000
b110 =
b101 A
b11 @
1(
#1690000
0(
#1695000
b111 =
1(
#1700000
0(
#1705000
b1000 =
1(
#1710000
0(
#1715000
b1001 =
1(
#1720000
0(
#1725000
b1010 =
1(
#1730000
0(
#1735000
b1011 =
1(
#1740000
0(
#1745000
b1100 =
1(
#1750000
0(
#1755000
b1101 =
1(
#1760000
0(
#1765000
b1110 =
1(
#1770000
0(
#1775000
b1111 =
1(
#1780000
0(
#1785000
b10000 =
1(
#1790000
0(
#1795000
b10001 =
1(
#1800000
0(
#1805000
b10010 =
1(
#1810000
0(
#1815000
b10011 =
1(
#1820000
0(
#1825000
b10100 =
1(
#1830000
0(
#1835000
b10101 =
1(
#1840000
0(
#1845000
b10110 =
1(
#1850000
0(
#1855000
b10111 =
1(
#1860000
0(
#1865000
b11000 =
1(
#1870000
0(
#1875000
b11001 =
1(
#1880000
0(
#1885000
b11010 =
1(
#1890000
0(
#1895000
b11011 =
1(
#1900000
0(
#1905000
b11100 =
1(
#1910000
0(
#1915000
b11101 =
1(
#1920000
0(
#1925000
b11110 =
1(
#1930000
0(
#1935000
b11111 =
1(
#1940000
0(
#1945000
b100000 =
1(
#1950000
0(
#1955000
b100001 =
1(
#1960000
0(
#1965000
b100010 =
1(
#1970000
0(
#1975000
b100011 =
1(
#1980000
0(
#1985000
b100100 =
1(
#1990000
0(
#1995000
b100101 =
1(
#2000000
0(
#2005000
b100110 =
1(
#2010000
0(
#2015000
b100111 =
1(
#2020000
0(
#2025000
b101000 =
1(
#2030000
0(
#2035000
b101001 =
1(
#2040000
0(
#2045000
b101010 =
1(
#2050000
0(
#2055000
b101011 =
1(
#2060000
0(
#2065000
b101100 =
1(
#2070000
0(
#2075000
b101101 =
1(
#2080000
0(
#2085000
b101110 =
1(
#2090000
0(
#2095000
b101111 =
1(
#2100000
0(
#2105000
b110000 =
1(
#2110000
0(
#2115000
b110001 =
1(
#2120000
0(
#2125000
b110010 =
1(
#2130000
0(
#2135000
b100 B
1(
#2140000
0(
#2145000
b101 B
b11 >
b1 <
1(
#2150000
0(
#2155000
b110 B
1"
1(
#2160000
0(
#2165000
b0 B
0"
1(
#2170000
0(
#2175000
1(
#2180000
0(
#2185000
1(
#2190000
0(
#2195000
1(
#2200000
0(
#2205000
b1 B
b0 <
b0 ;
b0 >
b0 =
b11 D
b10 C
b110010 E
1(
1+
b1000000011 ,
b1000000011 /
b10 -
#2210000
0(
#2215000
b1 =
1(
0+
#2220000
0(
#2225000
b10 =
1(
#2230000
0(
#2235000
b11 =
1(
#2240000
0(
#2245000
b100 =
1(
#2250000
0(
#2255000
b101 =
1(
#2260000
0(
#2265000
b110 =
1(
#2270000
0(
#2275000
b111 =
1(
#2280000
0(
#2285000
b1000 =
1(
#2290000
0(
#2295000
b1001 =
1(
#2300000
0(
#2305000
b1010 =
1(
#2310000
0(
#2315000
b1011 =
1(
#2320000
0(
#2325000
b1100 =
1(
#2330000
0(
#2335000
b1101 =
1(
#2340000
0(
#2345000
b1110 =
1(
#2350000
0(
#2355000
b1111 =
1(
#2360000
0(
#2365000
b10000 =
1(
#2370000
0(
#2375000
b10001 =
1(
#2380000
0(
#2385000
b10010 =
1(
#2390000
0(
#2395000
b10011 =
1(
#2400000
0(
#2405000
b10100 =
1(
#2410000
0(
#2415000
b10101 =
1(
#2420000
0(
#2425000
b10110 =
1(
#2430000
0(
#2435000
b10111 =
1(
#2440000
0(
#2445000
b11000 =
1(
#2450000
0(
#2455000
b11001 =
1(
#2460000
0(
#2465000
b11010 =
1(
#2470000
0(
#2475000
b11011 =
1(
#2480000
0(
#2485000
b11100 =
1(
#2490000
0(
#2495000
b11101 =
1(
#2500000
0(
#2505000
b11110 =
1(
#2510000
0(
#2515000
b11111 =
1(
#2520000
0(
#2525000
b100000 =
1(
#2530000
0(
#2535000
b100001 =
1(
#2540000
0(
#2545000
b100010 =
1(
#2550000
0(
#2555000
b100011 =
1(
#2560000
0(
#2565000
b100100 =
1(
#2570000
0(
#2575000
b100101 =
1(
#2580000
0(
#2585000
b100110 =
1(
#2590000
0(
#2595000
b100111 =
1(
#2600000
0(
#2605000
b101000 =
1(
#2610000
0(
#2615000
b101001 =
1(
#2620000
0(
#2625000
b101010 =
1(
#2630000
0(
#2635000
b101011 =
1(
#2640000
0(
#2645000
b101100 =
1(
#2650000
0(
#2655000
b101101 =
1(
#2660000
0(
#2665000
b101110 =
1(
#2670000
0(
#2675000
b101111 =
1(
#2680000
0(
#2685000
b110000 =
1(
#2690000
0(
#2695000
b110001 =
1(
#2700000
0(
#2705000
b110010 =
1(
#2710000
0(
#2715000
b10 B
b0 =
1(
#2720000
0(
#2725000
b11 B
b0 A
b1111111111111 @
1(
#2730000
0(
#2735000
b1 =
b1010 @
1(
#2740000
0(
#2745000
b10 =
b1 A
b10 @
1(
#2750000
0(
#2755000
b11 =
1(
#2760000
0(
#2765000
b100 =
1(
#2770000
0(
#2775000
b101 =
1(
#2780000
0(
#2785000
b110 =
1(
#2790000
0(
#2795000
b111 =
1(
#2800000
0(
#2805000
b1000 =
1(
#2810000
0(
#2815000
b1001 =
1(
#2820000
0(
#2825000
b1010 =
1(
#2830000
0(
#2835000
b1011 =
1(
#2840000
0(
#2845000
b1100 =
1(
#2850000
0(
#2855000
b1101 =
1(
#2860000
0(
#2865000
b1110 =
1(
#2870000
0(
#2875000
b1111 =
1(
#2880000
0(
#2885000
b10000 =
1(
#2890000
0(
#2895000
b10001 =
1(
#2900000
0(
#2905000
b10010 =
1(
#2910000
0(
#2915000
b10011 =
1(
#2920000
0(
#2925000
b10100 =
1(
#2930000
0(
#2935000
b10101 =
1(
#2940000
0(
#2945000
b10110 =
1(
#2950000
0(
#2955000
b10111 =
1(
#2960000
0(
#2965000
b11000 =
1(
#2970000
0(
#2975000
b11001 =
1(
#2980000
0(
#2985000
b11010 =
1(
#2990000
0(
#2995000
b11011 =
1(
#3000000
0(
#3005000
b11100 =
1(
#3010000
0(
#3015000
b11101 =
1(
#3020000
0(
#3025000
b11110 =
1(
#3030000
0(
#3035000
b11111 =
1(
#3040000
0(
#3045000
b100000 =
1(
#3050000
0(
#3055000
b100001 =
1(
#3060000
0(
#3065000
b100010 =
1(
#3070000
0(
#3075000
b100011 =
1(
#3080000
0(
#3085000
b100100 =
1(
#3090000
0(
#3095000
b100101 =
1(
#3100000
0(
#3105000
b100110 =
1(
#3110000
0(
#3115000
b100111 =
1(
#3120000
0(
#3125000
b101000 =
1(
#3130000
0(
#3135000
b101001 =
1(
#3140000
0(
#3145000
b101010 =
1(
#3150000
0(
#3155000
b101011 =
1(
#3160000
0(
#3165000
b101100 =
1(
#3170000
0(
#3175000
b101101 =
1(
#3180000
0(
#3185000
b101110 =
1(
#3190000
0(
#3195000
b101111 =
1(
#3200000
0(
#3205000
b110000 =
1(
#3210000
0(
#3215000
b110001 =
1(
#3220000
0(
#3225000
b110010 =
1(
#3230000
0(
#3235000
b100 B
1(
#3240000
0(
#3245000
b10 B
b1 >
b1 ;
1(
#3250000
0(
#3255000
b11 B
b0 =
b0 A
b1111111111111 @
1(
#3260000
0(
#3265000
b1 =
b1010 @
1(
#3270000
0(
#3275000
b10 =
1(
#3280000
0(
#3285000
b11 =
b10 A
b11 @
1(
#3290000
0(
#3295000
b100 =
b11 A
b10 @
1(
#3300000
0(
#3305000
b101 =
1(
#3310000
0(
#3315000
b110 =
1(
#3320000
0(
#3325000
b111 =
1(
#3330000
0(
#3335000
b1000 =
1(
#3340000
0(
#3345000
b1001 =
1(
#3350000
0(
#3355000
b1010 =
1(
#3360000
0(
#3365000
b1011 =
1(
#3370000
0(
#3375000
b1100 =
1(
#3380000
0(
#3385000
b1101 =
1(
#3390000
0(
#3395000
b1110 =
1(
#3400000
0(
#3405000
b1111 =
1(
#3410000
0(
#3415000
b10000 =
1(
#3420000
0(
#3425000
b10001 =
1(
#3430000
0(
#3435000
b10010 =
1(
#3440000
0(
#3445000
b10011 =
1(
#3450000
0(
#3455000
b10100 =
1(
#3460000
0(
#3465000
b10101 =
1(
#3470000
0(
#3475000
b10110 =
1(
#3480000
0(
#3485000
b10111 =
1(
#3490000
0(
#3495000
b11000 =
1(
#3500000
0(
#3505000
b11001 =
1(
#3510000
0(
#3515000
b11010 =
1(
#3520000
0(
#3525000
b11011 =
1(
#3530000
0(
#3535000
b11100 =
1(
#3540000
0(
#3545000
b11101 =
1(
#3550000
0(
#3555000
b11110 =
1(
#3560000
0(
#3565000
b11111 =
1(
#3570000
0(
#3575000
b100000 =
1(
#3580000
0(
#3585000
b100001 =
1(
#3590000
0(
#3595000
b100010 =
1(
#3600000
0(
#3605000
b100011 =
1(
#3610000
0(
#3615000
b100100 =
1(
#3620000
0(
#3625000
b100101 =
1(
#3630000
0(
#3635000
b100110 =
1(
#3640000
0(
#3645000
b100111 =
1(
#3650000
0(
#3655000
b101000 =
1(
#3660000
0(
#3665000
b101001 =
1(
#3670000
0(
#3675000
b101010 =
1(
#3680000
0(
#3685000
b101011 =
1(
#3690000
0(
#3695000
b101100 =
1(
#3700000
0(
#3705000
b101101 =
1(
#3710000
0(
#3715000
b101110 =
1(
#3720000
0(
#3725000
b101111 =
1(
#3730000
0(
#3735000
b110000 =
1(
#3740000
0(
#3745000
b110001 =
1(
#3750000
0(
#3755000
b110010 =
1(
#3760000
0(
#3765000
b100 B
1(
#3770000
0(
#3775000
b10 B
b10 >
b1 <
1(
#3780000
0(
#3785000
b11 B
b0 =
b0 A
b1111111111111 @
1(
#3790000
0(
#3795000
b1 =
b1010 @
1(
#3800000
0(
#3805000
b10 =
1(
#3810000
0(
#3815000
b11 =
b10 A
b11 @
1(
#3820000
0(
#3825000
b100 =
1(
#3830000
0(
#3835000
b101 =
1(
#3840000
0(
#3845000
b110 =
1(
#3850000
0(
#3855000
b111 =
1(
#3860000
0(
#3865000
b1000 =
1(
#3870000
0(
#3875000
b1001 =
1(
#3880000
0(
#3885000
b1010 =
1(
#3890000
0(
#3895000
b1011 =
1(
#3900000
0(
#3905000
b1100 =
1(
#3910000
0(
#3915000
b1101 =
1(
#3920000
0(
#3925000
b1110 =
1(
#3930000
0(
#3935000
b1111 =
1(
#3940000
0(
#3945000
b10000 =
1(
#3950000
0(
#3955000
b10001 =
1(
#3960000
0(
#3965000
b10010 =
1(
#3970000
0(
#3975000
b10011 =
1(
#3980000
0(
#3985000
b10100 =
1(
#3990000
0(
#3995000
b10101 =
1(
#4000000
0(
#4005000
b10110 =
1(
#4010000
0(
#4015000
b10111 =
1(
#4020000
0(
#4025000
b11000 =
1(
#4030000
0(
#4035000
b11001 =
1(
#4040000
0(
#4045000
b11010 =
1(
#4050000
0(
#4055000
b11011 =
1(
#4060000
0(
#4065000
b11100 =
1(
#4070000
0(
#4075000
b11101 =
1(
#4080000
0(
#4085000
b11110 =
1(
#4090000
0(
#4095000
b11111 =
1(
#4100000
0(
#4105000
b100000 =
1(
#4110000
0(
#4115000
b100001 =
1(
#4120000
0(
#4125000
b100010 =
1(
#4130000
0(
#4135000
b100011 =
1(
#4140000
0(
#4145000
b100100 =
1(
#4150000
0(
#4155000
b100101 =
1(
#4160000
0(
#4165000
b100110 =
1(
#4170000
0(
#4175000
b100111 =
1(
#4180000
0(
#4185000
b101000 =
1(
#4190000
0(
#4195000
b101001 =
1(
#4200000
0(
#4205000
b101010 =
1(
#4210000
0(
#4215000
b101011 =
1(
#4220000
0(
#4225000
b101100 =
1(
#4230000
0(
#4235000
b101101 =
1(
#4240000
0(
#4245000
b101110 =
1(
#4250000
0(
#4255000
b101111 =
1(
#4260000
0(
#4265000
b110000 =
1(
#4270000
0(
#4275000
b110001 =
1(
#4280000
0(
#4285000
b110010 =
1(
#4290000
0(
#4295000
b100 B
1(
#4300000
0(
#4305000
b101 B
b11 >
b10 <
1(
#4310000
0(
#4315000
b110 B
1"
1!
1(
#4320000
0(
#4325000
b0 B
0"
1(
#4330000
0(
